formatkit/__init__.py
formatkit/formatkit.py
formatkit-1.1.2.dist-info/METADATA
formatkit-1.1.2.dist-info/WHEEL
formatkit-1.1.2.dist-info/top_level.txt
formatkit-1.1.2.dist-info/RECORD
