Metadata-Version: 2.1
Name: formatkit
Version: 1.1.2
Summary: Great terminal formatting tool
Home-page: UNKNOWN
Author: UNKNOWN
Author-email: UNKNOWN
License: UNKNOWN
Keywords: python,color,formatkit,format,formatting-tools
Platform: UNKNOWN
